<?xml version="1.0" encoding="utf-8" ?><dwsync><file name="jquery-1.11.1.min.js" server="websys3.stern.nyu.edu" local="3501351167" remote="3558195484125454591" Dst="-1" /><file name="jquery.mobile-1.4.5.min.js" server="websys3.stern.nyu.edu" local="3497621626" remote="3558195484121725050" Dst="-1" /><file name="jquery.mobile.inline-svg-1.4.5.css" server="websys3.stern.nyu.edu" local="3497621626" remote="2898334988145096826" Dst="-1" /><file name="jquery.mobile.theme-1.4.5.css" server="websys3.stern.nyu.edu" local="3497621626" remote="2896049790665717882" Dst="-1" /><file name="jquery.mobile.theme-1.4.5.min.css" server="websys3.stern.nyu.edu" local="3497621626" remote="3558479501719074938" Dst="-1" /><file name="jquery.mobile.icons-1.4.5.css" server="websys3.stern.nyu.edu" local="3497621626" remote="3826155813659572346" Dst="-1" /><file name="jquery.mobile.icons-1.4.5.min.css" server="websys3.stern.nyu.edu" local="3497621626" remote="3825557198297725050" Dst="-1" /><file name="jquery.mobile.inline-png-1.4.5.css" server="websys3.stern.nyu.edu" local="3497621626" remote="1949979408592369786" Dst="-1" /><file name="jquery.mobile.structure-1.4.5.css" server="websys3.stern.nyu.edu" local="3497621626" remote="3917209051615295610" Dst="-1" /><file name="jquery.mobile.external-png-1.4.5.css" server="websys3.stern.nyu.edu" local="3497621626" remote="3824016026592966778" Dst="-1" /><file name="jquery.mobile-1.4.5.zip" server="websys3.stern.nyu.edu" local="3501351036" remote="7796318332" Dst="-1" /><file name="jquery.mobile.structure-1.4.5.min.css" server="websys3.stern.nyu.edu" local="3497621626" remote="3416500458577557626" Dst="-1" /><file name="jquery.mobile-1.4.5.js" server="websys3.stern.nyu.edu" local="3497621626" remote="7792588922" Dst="-1" /><file name="jquery.mobile-1.4.5.css" server="websys3.stern.nyu.edu" local="3497621626" remote="3333277530117994618" Dst="-1" /><file name="jquery.mobile.inline-svg-1.4.5.min.css" server="websys3.stern.nyu.edu" local="3497621626" remote="3333584156423190650" Dst="-1" /><file name="jquery.mobile-1.4.5.min.map" server="websys3.stern.nyu.edu" local="3497621626" remote="7792588922" Dst="-1" /><file name="jquery.mobile-1.4.5.min.css" server="websys3.stern.nyu.edu" local="3497621626" remote="3336742091257116794" Dst="-1" /><file name="jquery.mobile.external-png-1.4.5.min.css" server="websys3.stern.nyu.edu" local="3497621626" remote="3917741215243139194" Dst="-1" /><file name="jquery.mobile.inline-png-1.4.5.min.css" server="websys3.stern.nyu.edu" local="3497621626" remote="3336460891158313082" Dst="-1" /></dwsync>