<?xml version="1.0" encoding="utf-8" ?><dwsync><file name="jquery-logo.png" server="websys3.stern.nyu.edu" local="3497621626" remote="3416842887730133114" Dst="-1" /><file name="newyork.jpg" server="websys3.stern.nyu.edu" local="3497621626" remote="3553525720799606906" Dst="-1" /><file name="buenosaires.jpg" server="websys3.stern.nyu.edu" local="3497621626" remote="3673505391695198330" Dst="-1" /><file name="paris.jpg" server="websys3.stern.nyu.edu" local="3497621626" remote="3343508073497589882" Dst="-1" /><file name="capetown.jpg" server="websys3.stern.nyu.edu" local="3497621626" remote="3673505391695198330" Dst="-1" /><file name="seoul.jpg" server="websys3.stern.nyu.edu" local="3497621626" remote="3673505391695198330" Dst="-1" /><file name="sydney.jpg" server="websys3.stern.nyu.edu" local="3497621626" remote="3343508073497589882" Dst="-1" /><file name="album-bb.jpg" server="websys3.stern.nyu.edu" local="3497621626" remote="1304987196041295994" Dst="-1" /><file name="album-hc.jpg" server="websys3.stern.nyu.edu" local="3497621626" remote="1304987196041295994" Dst="-1" /><file name="album-p.jpg" server="websys3.stern.nyu.edu" local="3497621626" remote="1304987196041295994" Dst="-1" /><file name="album-ok.jpg" server="websys3.stern.nyu.edu" local="3497621626" remote="1304987196041295994" Dst="-1" /><file name="album-ws.jpg" server="websys3.stern.nyu.edu" local="3497621626" remote="1304987196041295994" Dst="-1" /><file name="album-rh.jpg" server="websys3.stern.nyu.edu" local="3497621626" remote="1304987196041295994" Dst="-1" /><file name="album-xx.jpg" server="websys3.stern.nyu.edu" local="3497621626" remote="1304987196041295994" Dst="-1" /><file name="album-mg.jpg" server="websys3.stern.nyu.edu" local="3497621626" remote="1304987196041295994" Dst="-1" /><file name="album-ag.jpg" server="websys3.stern.nyu.edu" local="3497621626" remote="1304987196041295994" Dst="-1" /><file name="album-k.jpg" server="websys3.stern.nyu.edu" local="3497621626" remote="1304987196041295994" Dst="-1" /><file name="album-af.jpg" server="websys3.stern.nyu.edu" local="3497621626" remote="1304987196041295994" Dst="-1" /><file name="devices.png" server="websys3.stern.nyu.edu" local="3497621626" remote="3825857708569491578" Dst="-1" /><file name="apple.png" server="websys3.stern.nyu.edu" local="3497621626" remote="3623954800677845114" Dst="-1" /><file name="blackberry_10.png" server="websys3.stern.nyu.edu" local="3497621626" remote="3623954800677845114" Dst="-1" /><file name="lumia_800.png" server="websys3.stern.nyu.edu" local="3497621626" remote="3623954800677845114" Dst="-1" /><file name="galaxy_express.png" server="websys3.stern.nyu.edu" local="3497621626" remote="3623954800677845114" Dst="-1" /><file name="nexus_7.png" server="websys3.stern.nyu.edu" local="3497621626" remote="3623954800677845114" Dst="-1" /><file name="firefox_os.png" server="websys3.stern.nyu.edu" local="3497621626" remote="3623954800677845114" Dst="-1" /><file name="tizen.png" server="websys3.stern.nyu.edu" local="3497621626" remote="3623954800677845114" Dst="-1" /><file name="bg-pattern.png" server="websys3.stern.nyu.edu" local="3497621626" remote="2895393382223935610" Dst="-1" /><file name="bike.jpg" server="websys3.stern.nyu.edu" local="3497621626" remote="2895393382223935610" Dst="-1" /><file name="gf.png" server="websys3.stern.nyu.edu" local="3497621626" remote="3623140131281139834" Dst="-1" /><file name="de.png" server="websys3.stern.nyu.edu" local="3497621626" remote="3623140131281139834" Dst="-1" /><file name="gb.png" server="websys3.stern.nyu.edu" local="3497621626" remote="3623140131281139834" Dst="-1" /><file name="fi.png" server="websys3.stern.nyu.edu" local="3497621626" remote="3623140131281139834" Dst="-1" /><file name="us.png" server="websys3.stern.nyu.edu" local="3497621626" remote="3623140131281139834" Dst="-1" /><file name="phone_iphone5.png" server="websys3.stern.nyu.edu" local="3497621626" remote="3554572043552389242" Dst="-1" /><file name="phone_galaxy3.png" server="websys3.stern.nyu.edu" local="3497621626" remote="3554572043552389242" Dst="-1" /><file name="phone_lumia920.png" server="websys3.stern.nyu.edu" local="3497621626" remote="3554572043552389242" Dst="-1" /><file name="phone_onex.png" server="websys3.stern.nyu.edu" local="3497621626" remote="3554572043552389242" Dst="-1" /><file name="firefox-logo.png" server="websys3.stern.nyu.edu" local="3497621626" remote="3343508073497589882" Dst="-1" /><file name="bmw-thumb.jpg" server="websys3.stern.nyu.edu" local="3497621626" remote="3417993183051217018" Dst="-1" /><file name="landrover-thumb.jpg" server="websys3.stern.nyu.edu" local="3497621626" remote="3417993183051217018" Dst="-1" /><file name="tesla-thumb.jpg" server="websys3.stern.nyu.edu" local="3497621626" remote="3417993183051217018" Dst="-1" /><file name="album-bk.jpg" server="websys3.stern.nyu.edu" local="3497621626" remote="7792588922" Dst="-1" /><file name="bmw.jpg" server="websys3.stern.nyu.edu" local="3497621626" remote="7792588922" Dst="-1" /><file name="photo-portrait.jpg" server="websys3.stern.nyu.edu" local="3497621626" remote="3417019634224298106" Dst="-1" /><file name="tesla.jpg" server="websys3.stern.nyu.edu" local="3497621626" remote="7792588922" Dst="-1" /><file name="landrover.jpg" server="websys3.stern.nyu.edu" local="3497621626" remote="7792588922" Dst="-1" /><file name="photo-landscape.jpg" server="websys3.stern.nyu.edu" local="3497621626" remote="3417019634224298106" Dst="-1" /><file name="photo-run.jpeg" server="websys3.stern.nyu.edu" local="3497621626" remote="7792588922" Dst="-1" /></dwsync>